add_url/__init__.py
add_url-0.2.0.dist-info/WHEEL
add_url-0.2.0.dist-info/entry_points.txt
add_url-0.2.0.dist-info/METADATA
add_url-0.2.0.dist-info/RECORD
